event_time_format/Test_event_time_format.py
event_time_format/__init__.py
event_time_format/event_time_format.py
event_time_format-1.0.6.dist-info/LICENSE
event_time_format-1.0.6.dist-info/METADATA
event_time_format-1.0.6.dist-info/WHEEL
event_time_format-1.0.6.dist-info/top_level.txt
event_time_format-1.0.6.dist-info/RECORD
